aiq/__init__.py
aiq/churn/__init__.py
aiq/churn/utility.py
aiq/churn/algo/__init__.py
aiq/churn/algo/model_registry.py
aiq/churn/algo/evaluators/EvaluatorFactory.py
aiq/churn/algo/evaluators/__init__.py
aiq/churn/algo/evaluators/base.py
aiq/churn/algo/evaluators/classification.py
aiq/churn/algo/evaluators/regression.py
aiq/churn/algo/feature_selectors/FeatureSelectorFactory.py
aiq/churn/algo/feature_selectors/__init__.py
aiq/churn/algo/feature_selectors/base.py
aiq/churn/algo/feature_selectors/permutation.py
aiq/churn/algo/feature_selectors/rfecv.py
aiq/churn/algo/trainers/TrainerFactory.py
aiq/churn/algo/trainers/__init__.py
aiq/churn/algo/trainers/base.py
aiq/churn/algo/trainers/lightgbm.py
aiq/churn/algo/trainers/xgboost.py
aiq/churn/analytics/AIQAnalyticsJobScheduler.py
aiq/churn/analytics/__init__.py
aiq/churn/analytics/file_dataloader.py
aiq/churn/analytics/subscriberprofile_loader.py
aiq/churn/dao/__init__.py
aiq/churn/dao/db/AIQMysqlDBPool.py
aiq/churn/dao/db/ChurnTrainStatusDAO.py
aiq/churn/dao/db/SupportedAlgorithmDao.py
aiq/churn/dao/db/__init__.py
aiq/churn/main/AIQCoreAPP.py
aiq/churn/main/AIQCoreException.py
aiq/churn/main/__init__.py
aiq/churn/main/server/DumyTrainer.py
aiq/churn/main/server/PredictorServer.py
aiq/churn/main/server/__init__.py
aiq/churn/main/server/run_prediction.py
aiq/churn/main/server/controllers/ControllerFactory.py
aiq/churn/main/server/controllers/__init__.py
aiq/churn/main/server/controllers/v1/ChurnController.py
aiq/churn/main/server/controllers/v1/__init__.py
aiq/churn/main/server/dto/LoadModelResult.py
aiq/churn/main/server/dto/PredictionResult.py
aiq/churn/main/server/dto/PublishModelResult.py
aiq/churn/main/server/dto/StartTrainResult.py
aiq/churn/main/server/dto/__init__.py
aiq/churn/main/server/services/ChurnService.py
aiq/churn/main/server/services/__init__.py
aiq/churn/plugin/__init__.py
aiq/churn/plugin/inputs/DataCleaner.py
aiq/churn/plugin/inputs/DataExplorer.py
aiq/churn/plugin/inputs/DataTransformer.py
evol_aiq-1.0.0.post202512031655.dist-info/METADATA
evol_aiq-1.0.0.post202512031655.dist-info/WHEEL
evol_aiq-1.0.0.post202512031655.dist-info/top_level.txt
evol_aiq-1.0.0.post202512031655.dist-info/RECORD
