Metadata-Version: 2.4
Name: evol-aiq
Version: 1.0.0.post202512031655
Summary: Evolving AIQ base build
Author: Evolving AIQ Team (PD,RK)
Author-email: your.email@example.com
Requires-Dist: pandas
Requires-Dist: Flask
Requires-Dist: gunicorn
Requires-Dist: pyyaml
Requires-Dist: scikit-learn
Requires-Dist: matplotlib
Requires-Dist: numpy
Requires-Dist: joblib
Requires-Dist: fastapi
Requires-Dist: missingno
Requires-Dist: seaborn
Requires-Dist: lightgbm
Requires-Dist: xgboost
Requires-Dist: dash
Requires-Dist: dash_bootstrap_components
Requires-Dist: pyhive
Requires-Dist: sqlalchemy
Requires-Dist: thrift
Requires-Dist: thrift_sasl
Requires-Dist: orjson
Dynamic: author
Dynamic: author-email
Dynamic: requires-dist
Dynamic: summary
